aioctutilsDev/__init__.py
aioctutilsDev/functions.py
aioctutilsdev-0.1.9.dist-info/licenses/License.txt
aioctutilsdev-0.1.9.dist-info/METADATA
aioctutilsdev-0.1.9.dist-info/WHEEL
aioctutilsdev-0.1.9.dist-info/top_level.txt
aioctutilsdev-0.1.9.dist-info/RECORD
