Metadata-Version: 2.4
Name: aioctutilsDev
Version: 0.1.9
Summary: Extracting the metadata & source lineage items used in the Semantic Models in Microsoft Fabric
Author-email: Ponnam Sanjay <Ponnam.Sanjay@sonata-software.com>
License-Expression: MIT
Classifier: Programming Language :: Python :: 3
Classifier: Operating System :: OS Independent
Requires-Python: >=3.11
License-File: License.txt
Dynamic: license-file
